[
    {
        "model": "maze.mazequestion",
        "pk": 1,
        "fields": {
            "question_text": "첫 번째 미궁 문제입니다. 사과와 배 중 더 큰 것은?",
            "answer": "배",
            "hint": "과일 중에서 더 큰 것을 선택하세요.",
            "order": 1,
            "difficulty": "easy",
            "time_limit": 30
        }
    },
    {
        "model": "maze.mazequestion",
        "pk": 2,
        "fields": {
            "question_text": "초록색 불빛은 무엇을 의미할까요?",
            "answer": "진행",
            "hint": "신호등을 생각해보세요!",
            "order": 2,
            "difficulty": "medium",
            "time_limit": 60
        }
    }
]